Workbook

Sheet Premissas
A1: Premissa (edite as células AMARELAS) | B1: Valor | C1: Unidade / nota
A2: Câmbio USD/BRL | B2: 5.1 | C2: R$/US$
A3: Preço token input (classe Haiku) | B3: 1 | C3: US$/MTok
A4: Preço token output | B4: 5 | C4: US$/MTok
A5: Multiplicador cache read | B5: 0.1 | C5: x input
A6: Multiplicador cache write (info) | B6: 1.25 | C6: x input (amortizado, fora da fórmula)
A7: Cache hit (fração do input) | B7: 0.7 | C7: 0-1
A8: Tokens input por turno | B8: 22000 | C8: tokens
A9: Tokens output por turno | B9: 800 | C9: tokens
A10: Tokens por arquivo ingerido | B10: 50000 | C10: tokens
A11: Custo hora suporte/CS | B11: 60 | C11: R$/h
A12: Custo fixo operação/mês (sem folha) | B12: 10000 | C12: R$/mês
A13: Folha core/mês (linha separada) | B13: 20000 | C13: R$/mês
... A18: Fiscal: mensalidade por CNPJ | B18: 179 | C18: R$/CNPJ·mês
A20: Custo IA por turno de chat (R$) — fórmula | B20: =(B8*(1-B7)*B3 + B8*B7*B5*B3 + B9*B4)/1000000*B2 -> 0.061914 | C20: input não-cacheado + input cache-read + output, em R$
A21: Custo IA por arquivo ingerido (R$) — fórmula | B21: =B10*B3/1000000*B2 -> 0.255 | C21: ingestão = input puro

Sheet Linhas de custo
A1: Item | B1: Tipo | C1: Mín (R$) | D1: Máx (R$) | E1: Confiança | F1: Fonte
A2: Infra cloud — fase lancamento (até 30 clientes) | B2: fixo-mês | C2: 150 | D2: 800 | E2: alta | F2: cloud nacional em R$ (Magalu BV2/BV4 R$83-150 + storage no free tier do Cloudflare R2) até AWS sa-east-1 gerenciada (EC2 t3.large + RDS ≈ R$785) — pesquisa 2026-07-16
A3: Infra cloud — fase crescimento (até 150 clientes) | B3: fixo-mês | C3: 1800 | D3: 3500 | E3: media | F3: 2 nós + Postgres gerenciado HA + monitoração
A4: Infra cloud — fase escala (150+ clientes) | B4: fixo-mês | C4: 4000 | D4: 8000 | E4: baixa | F4: cluster gerenciado + réplica leitura + DR
A5: Custo fixo de operação (sem folha) | B5: fixo-mês | C5: 10000 | D5: 10000 | E5: premissa | F5: infra 800 (teto da fase lançamento) + suporte/CS 0,5 FTE 4000 + ferramentas/contab 1200 + marketing 4000 (sem folha core); com infra de crescimento, sobe ~1-2,7 mil
A6: Folha core (1 dev + fundador parcial) | B6: fixo-mês | C6: 20000 | D6: 20000 | E6: premissa | F6: 1 dev + fundador parcial — linha separada do CF
A7: Suporte/CS (por hora) | B7: por-cliente-mês | C7: 60 | D7: 60 | E7: premissa | F7: custo carregado CS/suporte BR
A8: IA — custo por turno de chat (faixa = cache hit 80% a 60%) | B8: por-interação | C8: 0.052 | D8: 0.072 | E8: media | F8: tokens 22000/800 @ US$1.0/5.0 MTok, cache hit central 70%, câmbio 5.1 — fórmula viva na aba Premissas
A9: IA — custo por arquivo ingerido | B9: por-interação | C9: 0.255 | D9: 0.255 | E9: media | F9: 50000 tokens de input
A10: Storage de PDFs (por GB·mês) | B10: por-DO | C10: 0.1 | D10: 0.25 | E10: media | F10: object storage BR ~R$0,10-0,25/GB·mês
A11: Banco/fila (por DO) | B11: por-DO | C11: 0.001 | D11: 0.001 | E11: premissa | F11: fila Postgres — custo marginal quase nulo
A12: Fiscal: custo do parceiro por documento | B12: referência | C12: 0.1 | D12: 0.14 | E12: alta | F12: Focus NFe: excedente R$0,10-0,12/doc; efetivo ≈R$0,137 no plano Growth (focusnfe.com.br/precos, 2026-07-16); CT-e/MDF-e inclusos na franquia única
A13: Fiscal: mensalidade da plataforma parceira | B13: referência | C13: 90 | D13: 548 | E13: alta | F13: Focus NFe: Solo R$89,90 (1 CNPJ, 100 docs) → Growth R$548 (CNPJs ilimitados, 4.000 docs) — sem setup, sem fidelidade
... A16: Fiscal: dev emissor próprio (one-off) | B16: referência | C16: 150000 | D16: 300000 | E16: baixa | F16: schema CT-e 4.0 + assinatura + contingência + MDF-e + homologação, sobre gateway do ContaViva-360 — só com >30k docs/mês

Sheet Planos
A1: Plano | B1: Porte | C1: Mensalidade (R$) [editável] | D1: Franquia DOs/mês | E1: Excedente R$/DO | F1: Contas CETESB | G1: Usuários | H1: IA interações/mês | I1: IA ingestões/mês | J1: SSO | K1: Retenção auditoria (m) | L1: Suporte h/mês | M1: Onboarding h | N1: Infra+storage rateado R$/mês [editável] | O1: R$/DO incluso | P1: Custo IA pior caso R$ | Q1: Custo suporte R$ | R1: Custo total/cliente R$ | S1: Margem bruta
A2: Essencial | B2: Micro/Autônomo | C2: 129 | D2: 30 | E2: 1.5 | F2: 1 | G2: 2 | H2: 100 | I2: 10 | J2: — | K2: 3 | L2: 0.25 | M2: 0 | N2: 8 | O2: =C2/D2 -> 4.3 | P2: =H2*Premissas!B20+I2*Premissas!B21 -> 8.7414 | Q2: =L2*Premissas!B11+M2*Premissas!B11/12 -> 15 | R2: =P2+Q2+N2 -> 31.7414 | S2: =(C2-R2)/C2 -> 0.75394264
A3: Profissional | B3: PME | C3: 349 | D3: 300 | E3: 1 | F3: 3 | G3: 5 | H3: 500 | I3: 50 | J3: — | K3: 12 | L3: 1 | M3: 1 | N3: 15 | O3: =C3/D3 -> 1.1633333 | P3: =H3*Premissas!B20+I3*Premissas!B21 -> 43.707 | Q3: =L3*Premissas!B11+M3*Premissas!B11/12 -> 65 | R3: =P3+Q3+N3 -> 123.707 | S3: =(C3-R3)/C3 -> 0.64553868
A4: Operacional (Pro) | B4: Operação intensiva | C4: 899 | D4: 1500 | E4: 0.7 | F4: 10 | G4: 15 | H4: 2000 | I4: 200 | J4: sim | K4: 24 | L4: 2 | M4: 4 | N4: 30 | O4: =C4/D4 -> 0.59933333 | P4: =H4*Premissas!B20+I4*Premissas!B21 -> 174.828 | Q4: =L4*Premissas!B11+M4*Premissas!B11/12 -> 140 | R4: =P4+Q4+N4 -> 344.828 | S4: =(C4-R4)/C4 -> 0.61643159
A5: Enterprise | B5: Grande operação | C5: 1990 | D5: 5000 | E5: 0.45 | F5: ilimitado* | G5: ilimitado* | H5: 5000 | I5: 500 | J5: sim | K5: 60 | L5: 5 | M5: 16 | N5: 60 | O5: =C5/D5 -> 0.398 | P5: =H5*Premissas!B20+I5*Premissas!B21 -> 437.07 | Q5: =L5*Premissas!B11+M5*Premissas!B11/12 -> 380 | R5: =P5+Q5+N5 -> 877.07 | S5: =(C5-R5)/C5 -> 0.55926131
A7: * ilimitado comercial com fair use contratual. Custo IA = pior caso (100% da cota usada); uso real tende a 30-50%.

Sheet Simulador de receita
A1: Simulador (mês 12) — edite os nº de clientes (AMARELO)
B2: Plano | C2: Conservador | D2: Base | E2: Otimista
B3: Essencial | C3: 15 | D3: 40 | E3: 80
B4: Profissional | C4: 8 | D4: 30 | E4: 70
B5: Operacional (Pro) | C5: 2 | D5: 8 | E5: 20
B6: Enterprise | C6: 0 | D6: 2 | E6: 6
B7: CNPJs com add-on fiscal | C7: 0 | D7: 0 | E7: 15
B9: MRR base (assinaturas) | C9: =SUMPRODUCT(C3:C6,Planos!C2:C5) -> 6525 | D9: =SUMPRODUCT(D3:D6,Planos!C2:C5) -> 26802 | E9: =SUMPRODUCT(E3:E6,Planos!C2:C5) -> 64670
B10: Receita fiscal/mês (add-on) | C10: =C7*(Premissas!B18+Premissas!B16*Premissas!B17) -> 0 | D10: =D7*(Premissas!B18+Premissas!B16*Premissas!B17) -> 0 | E10: =E7*(Premissas!B18+Premissas!B16*Premissas!B17) -> 5310
B11: MRR total (c/ extras k_extra) | C11: =C9*Premissas!B14+C10 -> 7177.5 | D11: =D9*Premissas!B14+D10 -> 29482.2 | E11: =E9*Premissas!B14+E10 -> 76447
B12: Custo variável total | C12: =SUMPRODUCT(C3:C6,Planos!R2:R5) -> 2155.433 | D12: =SUMPRODUCT(D3:D6,Planos!R2:R5) -> 9493.63 | E12: =SUMPRODUCT(E3:E6,Planos!R2:R5) -> 23357.782
B13: Custo fixo (sem folha) | C13: =Premissas!B12 -> 10000 | D13: =Premissas!B12 -> 10000 | E13: =Premissas!B12 -> 10000
B14: Resultado (sem folha) | C14: =C11-C12-C13 -> -4977.933 | D14: =D11-D12-D13 -> 9988.57 | E14: =E11-E12-E13 -> 43089.218
B15: Resultado (com folha core) | C15: =C14-Premissas!B13 -> -24977.933 | D15: =D14-Premissas!B13 -> -10011.43 | E15: =E14-Premissas!B13 -> 23089.218
B16: Margem bruta do cenário | C16: =IF(C11=0,0,(C11-C12)/C11) -> 0.69969586 | D16: =IF(D11=0,0,(D11-D12)/D11) -> 0.67798773 | E16: =IF(E11=0,0,(E11-E12)/E11) -> 0.69445783
B18: Break-even MRR (sem folha) | D18: =IF(D16=0,0,Premissas!B12/D16) -> 14749.529
B19: Break-even MRR (com folha) | D19: =IF(D16=0,0,(Premissas!B12+Premissas!B13)/D16) -> 44248.588
